fastapi18n/__init__.py
fastapi18n/decorators/__init__.py
fastapi18n/decorators/multilangual.py
fastapi18n/middlewares/__init__.py
fastapi18n/middlewares/middleware.py
fastapi18n/utils/__init__.py
fastapi18n/utils/commands.py
fastapi18n/utils/manage_translations.py
fastapi18n/wrappers/__init__.py
fastapi18n/wrappers/wrapper.py
fastapi18n-0.1.3.dist-info/licenses/LICENSE
tests/__init__.py
tests/models.py
tests/test_api.py
fastapi18n-0.1.3.dist-info/METADATA
fastapi18n-0.1.3.dist-info/WHEEL
fastapi18n-0.1.3.dist-info/entry_points.txt
fastapi18n-0.1.3.dist-info/top_level.txt
fastapi18n-0.1.3.dist-info/RECORD
