Metadata-Version: 2.4
Name: fastapi18n
Version: 0.1.3
Summary: Multilingual support middleware for FastAPI using gettext and Tortoise ORM
Home-page: https://github.com/klishinoleg/fastapi18n
Author: Klishin Oleg
Author-email: Oleg Klishin <klishinoleg@gmail.com>
License: MIT
Requires-Python: >=3.8
License-File: LICENSE
Requires-Dist: google-cloud-translate
Requires-Dist: typing_extensions
Requires-Dist: starlette
Requires-Dist: python-dotenv
Requires-Dist: Babel
Requires-Dist: contextvars
Requires-Dist: tortoise-orm==0.24.2
Requires-Dist: aerich
Requires-Dist: fastapi
Requires-Dist: fastapi-admin
Dynamic: author
Dynamic: home-page
Dynamic: license-file
Dynamic: requires-python
